quickfig/__init__.py
quickfig/data_types.py
quickfig/data_types_test.py
quickfig/definitions.py
quickfig/definitions_test.py
quickfig/quickfig.py
quickfig/quickfig_test.py
quickfig/type_converters.py
quickfig/type_converters_test.py
QuickFig-0.3.0.dist-info/LICENSE
QuickFig-0.3.0.dist-info/METADATA
QuickFig-0.3.0.dist-info/WHEEL
QuickFig-0.3.0.dist-info/top_level.txt
QuickFig-0.3.0.dist-info/RECORD
