Metadata-Version: 2.1
Name: QuickFig
Version: 0.3.0
Summary: Quick and Painless Python Config File Tool
Home-page: https://mlasevich.github.io/QuickFig/
Author: Michael Lasevich
Author-email: mlasevich+quickfig@gmail.com
License: Apache 2.0
Platform: UNKNOWN
Classifier: Programming Language :: Python :: 3
Classifier: Programming Language :: Python :: 2.7
Classifier: License :: OSI Approved :: Apache Software License
Classifier: Operating System :: OS Independent
Requires-Dist: PyYaml
Requires-Dist: future
